mediapills/__init__.py
mediapills/dependency_injection/__init__.py
mediapills/dependency_injection/exceptions.py
mediapills.dependency_injection-0.1.0.dist-info/LICENSE.md
mediapills.dependency_injection-0.1.0.dist-info/METADATA
mediapills.dependency_injection-0.1.0.dist-info/WHEEL
mediapills.dependency_injection-0.1.0.dist-info/top_level.txt
mediapills.dependency_injection-0.1.0.dist-info/RECORD
