Metadata-Version: 2.1
Name: mediapills.dependency-injection
Version: 0.1.0
Summary: A small Python dependency injection container
Home-page: https://github.com/mediapills/dependency_injection
Author: Andriy Yatskovets
Author-email: andriy.yatskovets@gmail.com
License: UNKNOWN
Project-URL: Bug Tracker, https://github.com/mediapills/dependency-injection/issues
Project-URL: Source Code, https://github.com/mediapills/dependency-injection
Platform: UNKNOWN
Classifier: Development Status :: 2 - Pre-Alpha
Classifier: Intended Audience :: Developers
Classifier: Intended Audience :: Education
Classifier: Programming Language :: Python
Classifier: Programming Language :: Python :: 3 :: Only
Classifier: Programming Language :: Python :: 3.6
Classifier: Programming Language :: Python :: 3.7
Classifier: Programming Language :: Python :: 3.8
Classifier: Programming Language :: Python :: 3.9
Classifier: License :: OSI Approved :: MIT License
Classifier: Topic :: Software Development :: Libraries :: Application Frameworks
Requires-Python: >=3.5
License-File: LICENSE.md
